{
	"rpcUrl": "https://api.devnet.solana.com",
	"dryRun": false,
	"keypairFilePath": "id.json",
	"computeUnitPriceMicroLamports": 100000,
	"baseMint": "H5XwKLit6Nt4tZPLisFR2sH1gvUBxvqX7LcihSi7cnEk",
	"quoteSymbol": "SOL",
	"dynamicAmmV2": {
		"creator": "4JTYKJAyS7eAXQRSxvMbmqgf6ajf3LR9JrAXpVEcww2q",
		"baseAmount": 100000000,
		"initPrice": 0.0001,
		"maxPrice": 1,
		"poolFees": {
			"maxBaseFeeBps": 5000,
			"minBaseFeeBps": 100,
			"numberOfPeriod": 10,
			"totalDuration": 600,
			"feeSchedulerMode": 0,
			"useDynamicFee": false,
			"dynamicFeeConfig": null
		},
		"hasAlphaVault": true,
		"collectFeeMode": 0,
		"activationType": "timestamp",
		"activationPoint": 1746808200
	},
	"alphaVault": {
		"poolType": "damm2",
		"alphaVaultType": "prorata",
		"depositingPoint": 1733626299,
		"startVestingPoint": 1746808201,
		"endVestingPoint": 1746808201,
		"maxBuyingCap": 10000,
		"individualDepositingCap": 1,
		"escrowFee": 0,
		"whitelistMode": "permissionless"
	}
}
